newspaperzw/Provider.py
newspaperzw/__init__.py
newspaperzw/news.py
newspaper_zw-1.1.0.dist-info/LICENSE
newspaper_zw-1.1.0.dist-info/METADATA
newspaper_zw-1.1.0.dist-info/WHEEL
newspaper_zw-1.1.0.dist-info/top_level.txt
newspaper_zw-1.1.0.dist-info/RECORD
