Metadata-Version: 2.1
Name: newspaper-zw
Version: 1.1.0
Summary: get newspaper from online leading Zimbabwe content providers
Home-page: https://github.com/DonnC/zim-newspaper
Author: Donald Chinhuru
Author-email: donychinhuru@gmail.com
License: MIT
Platform: UNKNOWN
Classifier: License :: OSI Approved :: MIT License
Classifier: Programming Language :: Python :: 3
Classifier: Operating System :: OS Independent
Requires-Dist: newspaper3k
Requires-Dist: nltk
